{
  "main": {
    "id": "19e7bde070a4f3c2",
    "type": "split",
    "children": [
      {
        "id": "1e35f691b80585a9",
        "type": "tabs",
        "children": [
          {
            "id": "3af6fcf541253c30",
            "type": "leaf",
            "state": {
              "type": "markdown",
              "state": {
                "file": "RPG/6 - Sistema/Relacionamento.md",
                "mode": "source",
                "source": false
              }
            }
          }
        ]
      }
    ],
    "direction": "vertical"
  },
  "left": {
    "id": "da22ad4de6bde1b6",
    "type": "split",
    "children": [
      {
        "id": "7f92c8b32f39d8d4",
        "type": "tabs",
        "children": [
          {
            "id": "7634633fcc5a0763",
            "type": "leaf",
            "state": {
              "type": "file-explorer",
              "state": {
                "sortOrder": "alphabetical"
              }
            }
          },
          {
            "id": "809f7c3093a5b389",
            "type": "leaf",
            "state": {
              "type": "search",
              "state": {
                "query": "",
                "matchingCase": false,
                "explainSearch": false,
                "collapseAll": false,
                "extraContext": false,
                "sortOrder": "alphabetical"
              }
            }
          },
          {
            "id": "9bbaeed94e7f4e22",
            "type": "leaf",
            "state": {
              "type": "bookmarks",
              "state": {}
            }
          }
        ]
      }
    ],
    "direction": "horizontal",
    "width": 300
  },
  "right": {
    "id": "f005bcd4a5f6b84f",
    "type": "split",
    "children": [
      {
        "id": "ada7cf1dc612c174",
        "type": "tabs",
        "children": [
          {
            "id": "4da6f95cc56d15b8",
            "type": "leaf",
            "state": {
              "type": "backlink",
              "state": {
                "file": "RPG/6 - Sistema/Relacionamento.md",
                "collapseAll": false,
                "extraContext": false,
                "sortOrder": "alphabetical",
                "showSearch": false,
                "searchQuery": "",
                "backlinkCollapsed": false,
                "unlinkedCollapsed": true
              }
            }
          },
          {
            "id": "bb31403a63dcd4b1",
            "type": "leaf",
            "state": {
              "type": "outgoing-link",
              "state": {
                "file": "RPG/6 - Sistema/Relacionamento.md",
                "linksCollapsed": false,
                "unlinkedCollapsed": true
              }
            }
          },
          {
            "id": "da7b4acc260fca89",
            "type": "leaf",
            "state": {
              "type": "tag",
              "state": {
                "sortOrder": "frequency",
                "useHierarchy": true
              }
            }
          },
          {
            "id": "b3a41768dcf4704f",
            "type": "leaf",
            "state": {
              "type": "outline",
              "state": {
                "file": "RPG/6 - Sistema/Relacionamento.md"
              }
            }
          }
        ]
      }
    ],
    "direction": "horizontal",
    "width": 300,
    "collapsed": true
  },
  "left-ribbon": {
    "hiddenItems": {
      "switcher:Open quick switcher": false,
      "graph:Open graph view": false,
      "canvas:Create new canvas": false,
      "daily-notes:Open today's daily note": false,
      "templates:Insert template": false,
      "command-palette:Open command palette": false
    }
  },
  "active": "3af6fcf541253c30",
  "lastOpenFiles": [
    "RPG/6 - Sistema/Karma.md",
    "RPG/6 - Sistema/Relacionamento.md",
    "RPG/5 - Aegis - Mecarnes - Mestrelas/Aegis - Categorias.md",
    "RPG/6 - Sistema/Atributos.md",
    "RPG/5 - Aegis - Mecarnes - Mestrelas/Aegis - Condições Lista.md",
    "RPG/5 - Aegis - Mecarnes - Mestrelas/Aegis - Conceito.md",
    "RPG/5 - Aegis - Mecarnes - Mestrelas/Aegis - Pactos.md",
    "RPG/6 - Sistema/Inimigos.md",
    "RPG/5 - Aegis - Mecarnes - Mestrelas/Aegis - Ações das Expressões.md",
    "RPG/5 - Aegis - Mecarnes - Mestrelas/Aegis - Expressões.md",
    "RPG/5 - Aegis - Mecarnes - Mestrelas/Aegis - Troca equivalente.md",
    "RPG/5 - Aegis - Mecarnes - Mestrelas/Aegis - Pontos Aegis.md",
    "RPG/6 - Sistema/Sistema de cansaço.md",
    "RPG/1 - Raça/Humano.md",
    "RPG/3 - Profissões/Artista Marcial.md",
    "RPG/1 - Raça/Zytherin.md",
    "RPG/1 - Raça/Meio-Sereia.md",
    "RPG/1 - Raça/Inumano.md",
    "RPG/6 - Sistema/Morrendo.md",
    "RPG/4 - Itens/Armas Corpo-a-Corpo.md",
    "RPG/4 - Itens/Armaduras.md",
    "RPG/3 - Profissões/Campeão da Anciã.md",
    "RPG/6 - Sistema/Condições.md",
    "RPG/6 - Sistema/Sanidade.md",
    "RPG/6 - Sistema/Maneiras de Ganhar Dinheiro.md",
    "RPG/6 - Sistema/Criação de Personagem.md"
  ]
}